pyailab.py
pyailab-0.0.3.dist-info/LICENSE
pyailab-0.0.3.dist-info/METADATA
pyailab-0.0.3.dist-info/WHEEL
pyailab-0.0.3.dist-info/top_level.txt
pyailab-0.0.3.dist-info/RECORD
