Metadata-Version: 2.1
Name: pyailab
Version: 0.0.3
Summary: artificial intelligence
Author: aiml department
Author-email: aiml5thsem@gmail.com
License: MIT
Keywords: artificial intelligence lab,ailab
Classifier: Programming Language :: Python :: 3
Classifier: License :: OSI Approved :: MIT License
Classifier: Operating System :: OS Independent
Requires-Python: >=3.7
License-File: LICENSE
